gym_wm/__init__.py
gym_wm/cli.py
gym_wm/py.typed
gym_wm/core/__init__.py
gym_wm/core/config.py
gym_wm/core/environments.py
gym_wm/core/generator.py
gym_wm/core/policies.py
gym_wm/core/visualize.py
gym_wm/utils/__init__.py
gym_wm/utils/inspect.py
gym_wm-0.1.1.dist-info/licenses/LICENSE
gym_wm-0.1.1.dist-info/METADATA
gym_wm-0.1.1.dist-info/WHEEL
gym_wm-0.1.1.dist-info/entry_points.txt
gym_wm-0.1.1.dist-info/top_level.txt
gym_wm-0.1.1.dist-info/RECORD
