Metadata-Version: 2.4
Name: gym-wm
Version: 0.1.1
Summary: A toolbox for generating offline datasets from Gymnasium environments for world-model research
Author-email: Ahmet Selim Canakci <ascanakci@gmail.com>
License-Expression: MIT
Project-URL: Repository, https://github.com/unknown/gym_wm_dataset_generator
Project-URL: Documentation, https://github.com/unknown/gym_wm_dataset_generator#readme
Keywords: reinforcement-learning,offline-rl,gymnasium,minari,world-models,robotics,datasets
Classifier: Development Status :: 4 - Beta
Classifier: Intended Audience :: Science/Research
Classifier: Programming Language :: Python :: 3
Classifier: Programming Language :: Python :: 3.11
Classifier: Programming Language :: Python :: 3.12
Classifier: Topic :: Scientific/Engineering :: Artificial Intelligence
Requires-Python: >=3.11
License-File: LICENSE
Requires-Dist: gymnasium>=1.0.0
Requires-Dist: gymnasium-robotics>=1.3.0
Requires-Dist: minari>=0.5.0
Requires-Dist: numpy>=1.24.0
Requires-Dist: typer>=0.12.0
Requires-Dist: rich>=13.0.0
Requires-Dist: loguru>=0.7.0
Requires-Dist: matplotlib>=3.7.0
Requires-Dist: imageio>=2.31.0
Requires-Dist: imageio-ffmpeg>=0.4.9
Provides-Extra: dev
Requires-Dist: pytest>=7.4.0; extra == "dev"
Requires-Dist: pytest-cov>=4.1.0; extra == "dev"
Requires-Dist: pytest-mock>=3.12.0; extra == "dev"
Requires-Dist: ruff>=0.8.0; extra == "dev"
Requires-Dist: mypy>=1.8.0; extra == "dev"
Requires-Dist: pre-commit>=3.6.0; extra == "dev"
Provides-Extra: test
Requires-Dist: pytest>=7.4.0; extra == "test"
Requires-Dist: pytest-cov>=4.1.0; extra == "test"
Requires-Dist: pytest-mock>=3.12.0; extra == "test"
Requires-Dist: hypothesis>=6.100.0; extra == "test"
Dynamic: license-file
